nornir_routeros/__init__.py
nornir_routeros/utils.py
nornir_routeros/plugins/__init__.py
nornir_routeros/plugins/connections/__init__.py
nornir_routeros/plugins/tasks/__init__.py
nornir_routeros/plugins/tasks/routeros_command.py
nornir_routeros/plugins/tasks/routeros_config_item.py
nornir_routeros/plugins/tasks/routeros_get.py
nornir_routeros-0.7.1.dist-info/METADATA
nornir_routeros-0.7.1.dist-info/WHEEL
nornir_routeros-0.7.1.dist-info/entry_points.txt
nornir_routeros-0.7.1.dist-info/licenses/LICENSE
nornir_routeros-0.7.1.dist-info/RECORD
