Metadata-Version: 2.4
Name: nornir_routeros
Version: 0.7.1
Summary: RouterOS API plugins for nornir
Author-email: Devon Mar <devon-mar@users.noreply.github.com>
License-File: LICENSE
Requires-Python: >=3.9
Requires-Dist: jinja2<4.0,>=2.11.2
Requires-Dist: routeros-api<0.22,>=0.18
